airflow_tools/__init__.py
airflow_tools/_version.py
airflow_tools/compression_utils.py
airflow_tools/data_lake_facade.py
airflow_tools/exceptions.py
airflow_tools/filesystems/__init__.py
airflow_tools/filesystems/filesystem_factory.py
airflow_tools/filesystems/filesystem_protocol.py
airflow_tools/filesystems/impl/__init__.py
airflow_tools/filesystems/impl/azure_databricks_volume_filesystem.py
airflow_tools/filesystems/impl/azure_file_share_filesystem.py
airflow_tools/filesystems/impl/blob_storage_filesystem.py
airflow_tools/filesystems/impl/google_cloud_storage_filesystem.py
airflow_tools/filesystems/impl/local_filesystem.py
airflow_tools/filesystems/impl/s3_filesystem.py
airflow_tools/filesystems/impl/sftp_filesystem.py
airflow_tools/notifications/slack/webhook.py
airflow_tools/providers/__init__.py
airflow_tools/providers/azure/__init__.py
airflow_tools/providers/azure/hooks/__init__.py
airflow_tools/providers/azure/hooks/azure_databricks.py
airflow_tools/providers/azure/hooks/azure_file_share.py
airflow_tools/providers/data_lake/__init__.py
airflow_tools/providers/data_lake/operators/__init__.py
airflow_tools/providers/data_lake/operators/data_lake.py
airflow_tools/providers/deltalake/__init__.py
airflow_tools/providers/deltalake/operators/__init__.py
airflow_tools/providers/deltalake/operators/duckdb_to_deltalake.py
airflow_tools/providers/deltalake/operators/filesystem_to_database.py
airflow_tools/providers/deltalake/sensors/__init__.py
airflow_tools/providers/deltalake/sensors/filesystem_file.py
airflow_tools/providers/filesystem/__init__.py
airflow_tools/providers/filesystem/operators/__init__.py
airflow_tools/providers/filesystem/operators/filesystem.py
airflow_tools/providers/filesystem/operators/http_to_filesystem.py
airflow_tools/providers/filesystem/tasks.py
airflow_tools/providers/http_to_data_lake/__init__.py
airflow_tools/providers/http_to_data_lake/operators/__init__.py
airflow_tools/providers/http_to_data_lake/operators/http_to_data_lake.py
airflow_tools-0.11.1.dist-info/LICENSE.txt
airflow_tools-0.11.1.dist-info/METADATA
airflow_tools-0.11.1.dist-info/WHEEL
airflow_tools-0.11.1.dist-info/entry_points.txt
airflow_tools-0.11.1.dist-info/RECORD
