Metadata-Version: 2.3
Name: airflow-tools
Version: 0.11.1
Summary: 
Author: Biel Llobera
Author-email: biel_llobera@dkl.digital
Requires-Python: >=3.9,<3.12
Classifier: Programming Language :: Python :: 3
Classifier: Programming Language :: Python :: 3.9
Classifier: Programming Language :: Python :: 3.10
Classifier: Programming Language :: Python :: 3.11
Requires-Dist: airflow-provider-duckdb (>=0.2.0,<0.3.0)
Requires-Dist: apache-airflow (>=2.8.0,<=2.9.1)
Requires-Dist: apache-airflow-providers-amazon (>=9.0.0,<10.0.0)
Requires-Dist: apache-airflow-providers-google (>=10.23.0,<11.0.0)
Requires-Dist: apache-airflow-providers-microsoft-azure (>=8.0.0,<9.0.0)
Requires-Dist: apache-airflow-providers-sftp (>=4.8.1,<5.0.0)
Requires-Dist: apache-airflow-providers-slack (>=8.5.1,<9.0.0)
Requires-Dist: boto3 (>=1.34.8,<2.0.0)
Requires-Dist: boto3-stubs (>=1.34.8,<2.0.0)
Requires-Dist: databricks-sdk (>=0.21.0,<0.22.0)
Requires-Dist: databricks-sql-connector (>=2,<3)
Requires-Dist: deltalake (>=0.17.4,<0.18.0)
Requires-Dist: flask-session (==0.5.0)
Requires-Dist: jmespath (>=1.0.1,<2.0.0)
Requires-Dist: pandas (>=2.1.1,<3.0.0)
Requires-Dist: pandas-stubs (>=2.1.4.231218,<3.0.0.0)
Requires-Dist: pendulum (>=2.1.2,<3.0.0)
Requires-Dist: sqlalchemy (==1.4.54)
Requires-Dist: toml (>=0.10.2,<0.11.0)
Requires-Dist: types-jmespath (>=1.0.2.7,<2.0.0.0)
Requires-Dist: types-toml (>=0.10.8.7,<0.11.0.0)
